{"usuarios":[{"nombre":"barclay","apellido":"barclay","email":"barclay@mail.com"},{"nombre":"barry","apellido":"barry","email":"barry@mail.com"},{"nombre":"bort","apellido":"bort","email":"bort@mail.com"},{"nombre":"Nuevo","apellido":"Usuario","email":"nuevo@usuario.com"},{"nombre":"Nuevo nuevo","apellido":"Usuario","email":"nuevonuevo@usuario.com","password":"$2y$10$CkJ\/kfTEkYDIpf4faU.KUOL6WmJAeknalL6gYIXaYcBHm5\/m2WiC6"},{"nombre":"Nuevo nuevo","apellido":"Usuario","email":"nuevonuevo@usuario.com","password":"$2y$10$yfQ.Z9wjHV.VA\/wLhL8tI.38LVYrkHuQjjp53PZDQOh2uGK5cX8TK"},{"nombre":"Nuevo nuevo","apellido":"Usuario","email":"123456@usuario.com","password":"$2y$10$KihY31Jw8dxo1AhcUmkTXOhG2rwx8n.q9bxOD1f8d13jXYeoxzsl."}]}